LICENSE
MANIFEST.in
README.md
requirements-test.txt
setup.py
bin/burlap-admin.py
burlap/__init__.py
burlap/apache.py
burlap/avahi.py
burlap/aws.py
burlap/bluetooth.py
burlap/buildbot.py
burlap/celery.py
burlap/cloudfront.py
burlap/common.py
burlap/constants.py
burlap/context.py
burlap/cron.py
burlap/db.py
burlap/deb.py
burlap/debug.py
burlap/decorators.py
burlap/deploy.py
burlap/disk.py
burlap/dj.py
burlap/dns.py
burlap/elasticsearch.py
burlap/exceptions.py
burlap/files.py
burlap/git.py
burlap/gpsd.py
burlap/group.py
burlap/host.py
burlap/inadyn.py
burlap/ip.py
burlap/jirahelper.py
burlap/js.py
burlap/locale.py
burlap/mail.py
burlap/manifest.py
burlap/memcached.py
burlap/mongodb.py
burlap/motion.py
burlap/mysql.py
burlap/network.py
burlap/networkmanager.py
burlap/notifier.py
burlap/ntp.py
burlap/openvpn.py
burlap/packager.py
burlap/phantomjs.py
burlap/pip.py
burlap/postgresql.py
burlap/project.py
burlap/python_setuptools.py
burlap/rabbitmq.py
burlap/raid.py
burlap/rpi.py
burlap/rpm.py
burlap/rsync.py
burlap/s3.py
burlap/security.py
burlap/selenium.py
burlap/service.py
burlap/settings.py
burlap/shelf.py
burlap/snort.py
burlap/ssh.py
burlap/sslhelper.py
burlap/supervisor.py
burlap/system.py
burlap/systemd.py
burlap/tarball.py
burlap/tasks.py
burlap/trackers.py
burlap/user.py
burlap/utils.py
burlap/vagrant.py
burlap/versioner.py
burlap/virtualbox.py
burlap/vm.py
burlap.egg-info/PKG-INFO
burlap.egg-info/SOURCES.txt
burlap.egg-info/dependency_links.txt
burlap.egg-info/not-zip-safe
burlap.egg-info/requires.txt
burlap.egg-info/top_level.txt
burlap/fixtures/requirements.txt
burlap/templates/apache/apache_httpd.template.conf
burlap/templates/apache/apache_modevasive.template.conf
burlap/templates/apache/apache_modsecurity.template.conf
burlap/templates/apache/apache_ports.template.conf
burlap/templates/apache/apache_site.template.conf
burlap/templates/apache/maintenance.html.template
burlap/templates/avahi/etc_avahi_avahi_daemon_conf
burlap/templates/buildbot/check_buildbot.sh.template
burlap/templates/buildbot/etc_crond_buildbot.template
burlap/templates/buildbot/supervisor.conf.template
burlap/templates/burlap/all_settings.yaml.template
