Metadata-Version: 2.1
Name: burlap
Version: 0.9.123
Summary: Fabric commands for simplifying server deployments
Home-page: https://gitlab.com/chrisspen/burlap
Author: Chris Spencer
Author-email: chrisspen@gmail.com
License: MIT
Classifier: Development Status :: 5 - Production/Stable
Classifier: Environment :: Console
Classifier: Intended Audience :: Developers
Classifier: Intended Audience :: System Administrators
Classifier: License :: OSI Approved :: MIT License
Classifier: Operating System :: Unix
Classifier: Operating System :: POSIX
Classifier: Programming Language :: Python
Classifier: Programming Language :: Python :: 3.9
Classifier: Topic :: Software Development
Classifier: Topic :: Software Development :: Build Tools
Classifier: Topic :: Software Development :: Libraries
Classifier: Topic :: Software Development :: Libraries :: Python Modules
Classifier: Topic :: System :: Software Distribution
Classifier: Topic :: System :: Systems Administration
License-File: LICENSE
Requires-Dist: fab-classic==1.19.2
Requires-Dist: fabric2==3.2.2
Requires-Dist: boto3==1.34.19
Requires-Dist: PyYAML>=3.11
Requires-Dist: feedparser>=5.1.3
Requires-Dist: pytz>=2014.4
Requires-Dist: python-dateutil>=2.2
Requires-Dist: lockfile>=0.9.1
Requires-Dist: requirements-parser>=0.1.0
Requires-Dist: Jinja2>=2.8
Requires-Dist: PyNaCl>=1.5.0
Provides-Extra: aws
Requires-Dist: boto>=2.49.0; extra == "aws"
